{
    "BITCOIN": {
        "date": "2022-08-23T16:00:28.816",
        "status": "OPEN",
        "reason": "SUCCESS",
        "dealStatus": "ACCEPTED",
        "epic": "CS.D.BITCOIN.CFD.IP",
        "expiry": "-",
        "dealReference": "C5YT6UJKASGTYNK",
        "dealId": "DIAAAAKECH6NWAS",
        "affectedDeals": [
            {
                "dealId": "DIAAAAKECH6NWAS",
                "status": "OPENED"
            }
        ],
        "level": 21425.7,
        "size": 0.02,
        "direction": "SELL",
        "stopLevel": 21962.5,
        "limitLevel": 20352.1,
        "stopDistance": null,
        "limitDistance": null,
        "guaranteedStop": false,
        "trailingStop": false,
        "profit": null,
        "profitCurrency": null
    },
    "ETHUSD": {
        "date": "2022-08-23T16:00:34.399",
        "status": "OPEN",
        "reason": "SUCCESS",
        "dealStatus": "ACCEPTED",
        "epic": "CS.D.ETHUSD.CFD.IP",
        "expiry": "-",
        "dealReference": "2PAY2NZPMECTYNK",
        "dealId": "DIAAAAKECHBRNAJ",
        "affectedDeals": [
            {
                "dealId": "DIAAAAKECHBRNAJ",
                "status": "OPENED"
            }
        ],
        "level": 1642.15,
        "size": 0.12,
        "direction": "BUY",
        "stopLevel": 1601.15,
        "limitLevel": 1724.15,
        "stopDistance": null,
        "limitDistance": null,
        "guaranteedStop": false,
        "trailingStop": false,
        "profit": null,
        "profitCurrency": null
    }
}